groqflow/__init__.py
groqflow/version.py
groqflow/common/__init__.py
groqflow/common/build.py
groqflow/common/onnx_helpers.py
groqflow/common/sdk_helpers.py
groqflow/groqmodel/__init__.py
groqflow/groqmodel/execute.py
groqflow/groqmodel/groqmodel.py
groqflow/groqmodel/remote.py
groqflow/justgroqit/__init__.py
groqflow/justgroqit/assemble_multichip.py
groqflow/justgroqit/compile.py
groqflow/justgroqit/export.py
groqflow/justgroqit/groqit.py
groqflow/justgroqit/ignition.py
groqflow-4.3.1.dist-info/METADATA
groqflow-4.3.1.dist-info/WHEEL
groqflow-4.3.1.dist-info/top_level.txt
groqflow-4.3.1.dist-info/RECORD
