Metadata-Version: 2.1
Name: groqflow
Version: 4.3.1
Summary: GroqFlow toolchain library
Home-page: https://github.com/groq/groqflow
Author: Groq
Author-email: sales@groq.com
License: MIT
Requires-Python: >=3.8, <3.11
Requires-Dist: mlagility ==3.3.1
Requires-Dist: onnx ==1.14.0
Requires-Dist: onnxruntime ==1.15.1
Requires-Dist: protobuf ==3.20.3
Requires-Dist: scikit-learn ==1.1.1
Requires-Dist: torch ==2.1.0
Requires-Dist: typeguard ==4.0.0
Provides-Extra: tensorflow
Requires-Dist: tensorflow-cpu >=2.8.1 ; extra == 'tensorflow'
Requires-Dist: tf2onnx >=1.12.0 ; extra == 'tensorflow'
